setup.py
odoo/addons/helpdesk_ticket_mail_message/CHANGELOG.md
odoo/addons/helpdesk_ticket_mail_message/README.rst
odoo/addons/helpdesk_ticket_mail_message/__init__.py
odoo/addons/helpdesk_ticket_mail_message/__manifest__.py
odoo/addons/helpdesk_ticket_mail_message/requirements.txt
odoo/addons/helpdesk_ticket_mail_message/data/helpdesk_data.xml
odoo/addons/helpdesk_ticket_mail_message/i18n/ca_ES.po
odoo/addons/helpdesk_ticket_mail_message/i18n/en_US.po
odoo/addons/helpdesk_ticket_mail_message/i18n/es.po
odoo/addons/helpdesk_ticket_mail_message/models/__init__.py
odoo/addons/helpdesk_ticket_mail_message/models/helpdesk_ticket.py
odoo/addons/helpdesk_ticket_mail_message/models/helpdesk_ticket_team.py
odoo/addons/helpdesk_ticket_mail_message/models/mail_mail.py
odoo/addons/helpdesk_ticket_mail_message/models/mail_message.py
odoo/addons/helpdesk_ticket_mail_message/models/mail_template.py
odoo/addons/helpdesk_ticket_mail_message/models/res_company.py
odoo/addons/helpdesk_ticket_mail_message/models/res_config_settings.py
odoo/addons/helpdesk_ticket_mail_message/static/description/icon.png
odoo/addons/helpdesk_ticket_mail_message/static/src/css/font-awesome.min.css
odoo/addons/helpdesk_ticket_mail_message/static/src/css/list_renderer.css
odoo/addons/helpdesk_ticket_mail_message/static/src/fonts/FontAwesome.otf
odoo/addons/helpdesk_ticket_mail_message/static/src/fonts/fontawesome-webfont.eot
odoo/addons/helpdesk_ticket_mail_message/static/src/fonts/fontawesome-webfont.svg
odoo/addons/helpdesk_ticket_mail_message/static/src/fonts/fontawesome-webfont.ttf
odoo/addons/helpdesk_ticket_mail_message/static/src/fonts/fontawesome-webfont.woff
odoo/addons/helpdesk_ticket_mail_message/static/src/fonts/fontawesome-webfont.woff2
odoo/addons/helpdesk_ticket_mail_message/static/src/js/composer_view.js
odoo/addons/helpdesk_ticket_mail_message/static/src/js/delete_message_confirm_view.js
odoo/addons/helpdesk_ticket_mail_message/static/src/js/list_renderer.js
odoo_addon_helpdesk_ticket_mail_message.egg-info/PKG-INFO
odoo_addon_helpdesk_ticket_mail_message.egg-info/SOURCES.txt
odoo_addon_helpdesk_ticket_mail_message.egg-info/dependency_links.txt
odoo_addon_helpdesk_ticket_mail_message.egg-info/not-zip-safe
odoo_addon_helpdesk_ticket_mail_message.egg-info/requires.txt
odoo_addon_helpdesk_ticket_mail_message.egg-info/top_level.txt